MANIFEST.in
README.md
ez_setup.py
setup.py
metaphor/__init__.py
metaphor/cythonlist.txt
metaphor/services_gm.txt
metaphor/version_gm.py
metaphor/chem_gm/__init__.py
metaphor/chem_gm/gmconstants.py
metaphor/chem_gm/requirements.txt
metaphor/chem_gm/api/GM_DEMO.py
metaphor/chem_gm/api/__init__.py
metaphor/chem_gm/api/_api_service.py
metaphor/chem_gm/api/_run.py
metaphor/chem_gm/api/api.py
metaphor/chem_gm/api/cleancfg.py
metaphor/chem_gm/api/demo_jupyter.py
metaphor/chem_gm/api/graphmachine_demo.ipynb
metaphor/chem_gm/api/module_analysis.py
metaphor/chem_gm/api/_run/__init.py
metaphor/chem_gm/api/_run/__main.py
metaphor/chem_gm/api/_run/_nn_gm_run.py
metaphor/chem_gm/components/__init__.py
metaphor/chem_gm/components/gmmEngine.py
metaphor/chem_gm/components/lex.py
metaphor/chem_gm/components/mplUtils.py
metaphor/chem_gm/components/updatemgr.py
metaphor/chem_gm/components/yacc.py
metaphor/chem_gm/core/GMmodel.py
metaphor/chem_gm/core/__init__.py
metaphor/chem_gm/core/atoms.cfg
metaphor/chem_gm/core/atoms.py
metaphor/chem_gm/core/bonds.py
metaphor/chem_gm/core/gmconst.py
metaphor/chem_gm/core/gmprograms.py
metaphor/chem_gm/core/gmtoolbox.c
metaphor/chem_gm/core/gmutils.c
metaphor/chem_gm/core/graphmachineworkshop.c
metaphor/chem_gm/core/metamolecule.c
metaphor/chem_gm/core/smilexer.py
metaphor/chem_gm/core/smiparserspec.py
metaphor/chem_gm/core/smitokens.py
metaphor_gm.egg-info/PKG-INFO
metaphor_gm.egg-info/SOURCES.txt
metaphor_gm.egg-info/dependency_links.txt
metaphor_gm.egg-info/not-zip-safe
metaphor_gm.egg-info/requires.txt
metaphor_gm.egg-info/top_level.txt